Bayes/BayesA.py
Bayes/BayesB.py
Bayes/BayesC.py
Bayes/__init__.py
Bayes/_bayesfromR.py
Bayes/_param_free_base_model.py
Bayes/bayesAfromR.py
Bayes/bayesBfromR.py
Bayes/bayesCfromR.py
bayes_xw-4.4.dist-info/licenses/LICENSE
bayes_xw-4.4.dist-info/METADATA
bayes_xw-4.4.dist-info/WHEEL
bayes_xw-4.4.dist-info/top_level.txt
bayes_xw-4.4.dist-info/RECORD
