Metadata-Version: 2.4
Name: Bayes-xw
Version: 4.4
Summary: 一个非常NB的包
Classifier: Programming Language :: Python :: 3.9
Classifier: License :: OSI Approved :: MIT License
Classifier: Operating System :: OS Independent
Requires-Python: >=3.10
License-File: LICENSE
Requires-Dist: absl-py>=2.3.1
Requires-Dist: aiohappyeyeballs>=2.6.1
Requires-Dist: aiohttp>=3.13.2
Requires-Dist: aiosignal>=1.4.0
Requires-Dist: aislib>=0.1.14a0
Requires-Dist: alembic>=1.16.5
Requires-Dist: annotated-types>=0.7.0
Requires-Dist: anyio>=4.12.0
Requires-Dist: astunparse>=1.6.3
Requires-Dist: async-timeout>=5.0.1
Requires-Dist: attrs>=25.4.0
Requires-Dist: autogen-agentchat>=0.2.40
Requires-Dist: autopage>=0.5.2
Requires-Dist: boto3>=1.40.69
Requires-Dist: botocore>=1.40.69
Requires-Dist: certifi>=2025.10.5
Requires-Dist: charset-normalizer>=3.4.4
Requires-Dist: cliff>=4.9.1
Requires-Dist: cmaes>=0.12.0
Requires-Dist: cmd2>=2.7.0
Requires-Dist: colorlog>=6.10.1
Requires-Dist: coverage>=7.10.7
Requires-Dist: cycler>=0.12.1
Requires-Dist: cython>=3.2.1
Requires-Dist: deprecated>=1.3.1
Requires-Dist: diskcache>=5.6.3
Requires-Dist: distro>=1.9.0
Requires-Dist: docker>=7.1.0
Requires-Dist: einops>=0.8.1
Requires-Dist: executing>=2.2.1
Requires-Dist: filelock>=3.19.1
Requires-Dist: flaml>=2.3.6
Requires-Dist: flatbuffers>=25.9.23
Requires-Dist: frozenlist>=1.8.0
Requires-Dist: fsspec>=2025.10.0
Requires-Dist: gast>=0.6.0
Requires-Dist: google-pasta>=0.2.0
Requires-Dist: greenlet>=3.2.4
Requires-Dist: grpcio>=1.76.0
Requires-Dist: h11>=0.16.0
Requires-Dist: h5py>=3.14.0
Requires-Dist: hf-xet>=1.2.0
Requires-Dist: httpcore>=1.0.9
Requires-Dist: httpx>=0.28.1
Requires-Dist: huggingface-hub>=0.36.0
Requires-Dist: idna>=3.11
Requires-Dist: iniconfig>=2.1.0
Requires-Dist: jiter>=0.12.0
Requires-Dist: jmespath>=1.0.1
Requires-Dist: joblib>=1.5.2
Requires-Dist: keras>=3.10.0
Requires-Dist: kiwisolver>=1.4.7
Requires-Dist: libclang>=18.1.1
Requires-Dist: lightgbm>=4.6.0
Requires-Dist: lightning>=2.5.6
Requires-Dist: lightning-utilities>=0.15.2
Requires-Dist: mako>=1.3.10
Requires-Dist: markdown>=3.9
Requires-Dist: markupsafe>=3.0.3
Requires-Dist: matplotlib>=3.9.4
Requires-Dist: matplotlib-inline>=0.2.1
Requires-Dist: ml-dtypes>=0.5.3
Requires-Dist: mpmath>=1.3.0
Requires-Dist: multidict>=6.7.0
Requires-Dist: namex>=0.1.0
Requires-Dist: networkx>=3.2.1
Requires-Dist: openai>=2.8.1
Requires-Dist: opt-einsum>=3.4.0
Requires-Dist: optree>=0.17.0
Requires-Dist: optuna>=2.10.0
Requires-Dist: pandas-plink>=2.2.9
Requires-Dist: parso>=0.8.5
Requires-Dist: patsy>=1.0.2
Requires-Dist: platformdirs>=4.4.0
Requires-Dist: pluggy>=1.6.0
Requires-Dist: prettytable>=3.16.0
Requires-Dist: prompt-toolkit>=3.0.52
Requires-Dist: propcache>=0.4.1
Requires-Dist: protobuf>=6.33.0
Requires-Dist: psutil>=7.1.3
Requires-Dist: py>=1.11.0
Requires-Dist: pydantic>=2.12.4
Requires-Dist: pydantic-core>=2.41.5
Requires-Dist: pyecharts>=2.0.9
Requires-Dist: pyparsing>=3.2.5
Requires-Dist: pyperclip>=1.11.0
Requires-Dist: pyro-api>=0.1.2
Requires-Dist: pyro-ppl>=1.9.1
Requires-Dist: pytest>=8.4.2
Requires-Dist: pytest-cov>=7.0.0
Requires-Dist: python-dotenv>=1.2.1
Requires-Dist: pytorch-lightning>=2.5.6
Requires-Dist: pyyaml>=6.0.3
Requires-Dist: regex>=2025.11.3
Requires-Dist: requests>=2.32.5
Requires-Dist: rich>=13.9.4
Requires-Dist: rich-argparse>=1.7.2
Requires-Dist: rpy2>=3.5.16
Requires-Dist: s3transfer>=0.14.0
Requires-Dist: safetensors>=0.7.0
Requires-Dist: scikit-learn>=1.6.1
Requires-Dist: simplejson>=3.20.2
Requires-Dist: sniffio>=1.3.1
Requires-Dist: sqlalchemy>=2.0.44
Requires-Dist: statsmodels>=0.14.5
Requires-Dist: stevedore>=5.5.0
Requires-Dist: swanlab>=0.7.5
Requires-Dist: sympy>=1.14.0
Requires-Dist: tensorboard>=2.20.0
Requires-Dist: tensorboard-data-server>=0.7.2
Requires-Dist: tensorflow>=2.20.0
Requires-Dist: termcolor>=3.1.0
Requires-Dist: threadpoolctl>=3.6.0
Requires-Dist: tiktoken>=0.12.0
Requires-Dist: tokenizers>=0.22.1
Requires-Dist: tomli>=2.3.0
Requires-Dist: torch>=2.8.0
Requires-Dist: torchmetrics>=1.8.2
Requires-Dist: torchvision>=0.23.0
Requires-Dist: tqdm>=4.67.1
Requires-Dist: transformers>=4.57.3
Requires-Dist: triton>=3.4.0
Requires-Dist: typing-extensions>=4.15.0
Requires-Dist: typing-inspection>=0.4.2
Requires-Dist: urllib3>=1.26.20
Requires-Dist: wcwidth>=0.2.14
Requires-Dist: werkzeug>=3.1.3
Requires-Dist: wrapt>=2.0.1
Requires-Dist: xarray>=2024.7.0
Requires-Dist: xgboost>=2.1.4
Requires-Dist: xlsxwriter>=3.2.9
Requires-Dist: yarl>=1.22.0
Requires-Dist: numpy>=1.26.4
Requires-Dist: pandas>=2.3.3
Requires-Dist: scipy>=1.13.1
Requires-Dist: seaborn>=0.13.2
Requires-Dist: bokeh>=3.4.2
Requires-Dist: dask>=2024.7.1
Requires-Dist: dask-expr>=1.1.9
Requires-Dist: distributed>=2024.7.1
Requires-Dist: numba>=0.60.0
Requires-Dist: llvmlite>=0.43.0
Requires-Dist: pyarrow>=16.1.0
Requires-Dist: lz4>=4.3.3
Requires-Dist: zstandard>=0.23.0
Requires-Dist: pillow>=11.3.0
Requires-Dist: jupyter_client>=8.6.3
Requires-Dist: jupyter_core>=5.8.1
Requires-Dist: ipython>=8.18.1
Requires-Dist: ipykernel>=6.30.1
Requires-Dist: tornado>=6.5.2
Requires-Dist: pyzmq>=27.0.2
Requires-Dist: jinja2>=3.1.6
Requires-Dist: traitlets>=5.14.3
Requires-Dist: click>=8.1.8
Requires-Dist: cloudpickle>=3.1.1
Requires-Dist: toolz>=1.0.0
Requires-Dist: cytoolz>=1.0.1
Requires-Dist: partd>=1.4.2
Requires-Dist: locket>=1.0.0
Requires-Dist: sortedcontainers>=2.4.0
Requires-Dist: tblib>=3.1.0
Requires-Dist: zict>=3.0.0
Requires-Dist: msgpack>=1.0.7
Requires-Dist: pygments>=2.19.2
Requires-Dist: python-dateutil>=2.9.0
Requires-Dist: pytz>=2025.2
Requires-Dist: six>=1.17.0
Requires-Dist: decorator>=5.2.1
Requires-Dist: pexpect>=4.9.0
Requires-Dist: ptyprocess>=0.7.0
Requires-Dist: pickleshare>=0.7.5
Requires-Dist: stack_data>=0.6.3
Requires-Dist: nest-asyncio>=1.6.0
Requires-Dist: exceptiongroup>=1.3.0
Requires-Dist: asttokens>=3.0.0
Requires-Dist: pure_eval>=0.2.3
Requires-Dist: importlib_metadata>=8.7.0
Requires-Dist: importlib_resources>=6.5.2
Requires-Dist: zipp>=3.23.0
Requires-Dist: cachetools>=6.1.0
Requires-Dist: markdown-it-py>=3.0.0
Requires-Dist: mdurl>=0.1.2
Requires-Dist: packaging>=25.0
Requires-Dist: pycparser>=2.22
Requires-Dist: simplegeneric>=0.8.1
Requires-Dist: olefile>=0.47
Requires-Dist: fonttools>=4.60.1
Requires-Dist: brotli>=1.1.0
Requires-Dist: xyzservices>=2025.10.0
Requires-Dist: pysocks>=1.7.1
Requires-Dist: tzlocal>=5.3
Requires-Dist: numexpr>=2.10.1
Requires-Dist: bottleneck>=1.4.2
Requires-Dist: hpack>=4.1.0
Requires-Dist: hyperframe>=6.1.0
Requires-Dist: h2>=4.2.0
Requires-Dist: contourpy>=1.3.0
Dynamic: classifier
Dynamic: description
Dynamic: license-file
Dynamic: requires-dist
Dynamic: requires-python
Dynamic: summary
